pystella/__init__.py
pystella/_git_rev.py
pystella/decomp.py
pystella/derivs.py
pystella/elementwise.py
pystella/expansion.py
pystella/histogram.py
pystella/output.py
pystella/reduction.py
pystella/sectors.py
pystella/stencil.py
pystella/step.py
pystella/field/__init__.py
pystella/field/diff.py
pystella/field/sympy.py
pystella/fourier/__init__.py
pystella/fourier/derivs.py
pystella/fourier/dft.py
pystella/fourier/poisson.py
pystella/fourier/projectors.py
pystella/fourier/rayleigh.py
pystella/fourier/spectra.py
pystella/multigrid/__init__.py
pystella/multigrid/relax.py
pystella/multigrid/transfer.py
pystella-2020.1.dist-info/LICENSE
pystella-2020.1.dist-info/METADATA
pystella-2020.1.dist-info/WHEEL
pystella-2020.1.dist-info/top_level.txt
pystella-2020.1.dist-info/RECORD
