Metadata-Version: 2.1
Name: pystella
Version: 2020.1
Summary: A code generator for grid-based PDE solving on CPUs and GPUs
Home-page: https://github.com/zachjweiner/pystella
Author: Zachary J Weiner
License: MIT
Project-URL: Documentation, https://pystella.readthedocs.io/en/latest/
Project-URL: Source, https://github.com/zachjweiner/pystella
Platform: UNKNOWN
Classifier: Development Status :: 5 - Production/Stable
Classifier: Intended Audience :: Developers
Classifier: Intended Audience :: Science/Research
Classifier: License :: OSI Approved :: MIT License
Classifier: Programming Language :: Python :: 3
Classifier: Topic :: Scientific/Engineering
Classifier: Topic :: Scientific/Engineering :: Physics
Classifier: Topic :: Software Development :: Code Generators
Requires-Python: >=3
Requires-Dist: numpy
Requires-Dist: pyopencl
Requires-Dist: loo.py (>=2018.2)
